secos/Decomposition.py
secos/__init__.py
secos/__main__.py
secos/models/__init__.py
secos/models/download.py
secos/models/load.py
secos/models/models.py
secos/utils/__init__.py
secos/utils/utils.py
noun_decomposition-0.0.8.dist-info/LICENSE.txt
noun_decomposition-0.0.8.dist-info/METADATA
noun_decomposition-0.0.8.dist-info/WHEEL
noun_decomposition-0.0.8.dist-info/top_level.txt
noun_decomposition-0.0.8.dist-info/RECORD
