Metadata-Version: 2.1
Name: noun-decomposition
Version: 0.0.8
Summary: Python module to decompose nouns based on the SECOS algorithm
Home-page: https://github.com/mhaugestad/noun-decomposition
Download-URL: https://github.com/mhaugestad/noun-decomposition/archive/refs/tags/0.0.8.tar.gz
Author: Mathias Haugestad
Author-email: mhaugestad@gmail.com
Requires-Python: >=3.6
License-File: LICENSE.txt
Requires-Dist: scipy
Requires-Dist: numpy
Requires-Dist: pytest
Requires-Dist: importlib-resources
Requires-Dist: requests
Requires-Dist: tqdm
